toml_i18n/__init__.py
toml_i18n/toml_i18n.py
toml_i18n-1.0.6.dist-info/LICENSE
toml_i18n-1.0.6.dist-info/METADATA
toml_i18n-1.0.6.dist-info/WHEEL
toml_i18n-1.0.6.dist-info/top_level.txt
toml_i18n-1.0.6.dist-info/RECORD
