Metadata-Version: 2.2
Name: toml_i18n
Version: 1.0.6
Summary: A lightweight localization module for Python projects
Author-email: Arved Klöhn <arved.kloehn@gmail.com>
License: MIT
Classifier: Programming Language :: Python :: 3
Classifier: License :: OSI Approved :: MIT License
Classifier: Operating System :: OS Independent
Requires-Python: >=3.7
License-File: LICENSE
Requires-Dist: tomli; python_version < "3.11"
